{"success":true,"data":[{"timestamp":"1747962000","name":"Amber Group","profit":"100702451871","dailyChange":0,"weeklyChange":0,"side":"-"},{"timestamp":"1747962000","name":"Bog-Pear-Weasel","profit":"322003133406","dailyChange":-3841082,"weeklyChange":-33889674,"side":"Short"},{"timestamp":"1747962000","name":"Bramble-Dark-Grasp","profit":"188700698523","dailyChange":0,"weeklyChange":0,"side":"-"},{"timestamp":"1747962000","name":"Chatter-Paper-Snout","profit":"363101430000","dailyChange":0,"weeklyChange":0,"side":"-"},{"timestamp":"1747962000","name":"Chocolate-Flint-Falcon","profit":"148363230756","dailyChange":0,"weeklyChange":0,"side":"-"},{"timestamp":"1747962000","name":"Crypto Research","profit":"176454784734","dailyChange":0,"weeklyChange":0,"side":"-"},{"timestamp":"1747962000","name":"Disco-Solar-Fang","profit":"277047426726","dailyChange":0,"weeklyChange":0,"side":"-"},{"timestamp":"1747962000","name":"Fern-Ebony-Slave","profit":"132547494767","dailyChange":0,"weeklyChange":0,"side":"-"},{"timestamp":"1747962000","name":"Honeysuckle-South-Rib","profit":"197802789481","dailyChange":0,"weeklyChange":0,"side":"-"},{"timestamp":"1747962000","name":"Hot-Relic-Fancier","profit":"421651590744","dailyChange":0,"weeklyChange":0,"side":"-"},{"timestamp":"1747962000","name":"Linen","profit":"128335961925","dailyChange":-4861630,"weeklyChange":-20394475,"side":"Long"},{"timestamp":"1747962000","name":"Mercury-Wood-Sprite","profit":"848333808919","dailyChange":0,"weeklyChange":0,"side":"-"},{"timestamp":"1747962000","name":"Paper-Feather-Stallion","profit":"405461699789","dailyChange":0,"weeklyChange":0,"side":"-"},{"timestamp":"1747962000","name":"Prairie-Ballistic-Palm","profit":"99160733287","dailyChange":6037,"weeklyChange":40727,"side":"Short"},{"timestamp":"1747962000","name":"Prong-Buttercup-Whale","profit":"110782133711","dailyChange":20109239,"weeklyChange":69774342,"side":"Long"},{"timestamp":"1747962000","name":"Quill-Rift-Hoof","profit":"170411543374","dailyChange":10810757,"weeklyChange":32041144,"side":"Short"},{"timestamp":"1747962000","name":"Ripple-Great-Koala","profit":"137068778663","dailyChange":0,"weeklyChange":0,"side":"-"},{"timestamp":"1747962000","name":"Sho00","profit":"107545673468","dailyChange":0,"weeklyChange":0,"side":"-"},{"timestamp":"1747962000","name":"Shubhodeep Das","profit":"197561007709","dailyChange":0,"weeklyChange":0,"side":"-"},{"timestamp":"1747962000","name":"Skitter-Peridot-Raven","profit":"165801269805","dailyChange":0,"weeklyChange":0,"side":"-"},{"timestamp":"1747962000","name":"SuDoResearch","profit":"127477304991","dailyChange":0,"weeklyChange":0,"side":"-"},{"timestamp":"1747962000","name":"Winter-Pink-Fang","profit":"123861815224","dailyChange":0,"weeklyChange":0,"side":"-"},{"timestamp":"1747962000","name":"Zinc-Short-Snap","profit":"93336822975","dailyChange":-8085330,"weeklyChange":-27487269,"side":"Long"},{"timestamp":"1747962000","name":"fhrp","profit":"331620529937","dailyChange":0,"weeklyChange":0,"side":"-"},{"timestamp":"1747962000","name":"xorq","profit":"127811730513","dailyChange":0,"weeklyChange":0,"side":"-"}]}