{"success":true,"data":[{"timestamp":"1702429200","name":"3dudescapital","profit":"253302205981","dailyChange":17636856,"weeklyChange":127696472,"side":"Short"},{"timestamp":"1702429200","name":"Amber Group","profit":"100702451871","dailyChange":0,"weeklyChange":0,"side":"-"},{"timestamp":"1702429200","name":"Bog-Pear-Weasel","profit":"322138399019","dailyChange":216603887,"weeklyChange":150488184,"side":"Short"},{"timestamp":"1702429200","name":"Bramble-Dark-Grasp","profit":"188700698523","dailyChange":0,"weeklyChange":0,"side":"-"},{"timestamp":"1702429200","name":"Chatter-Paper-Snout","profit":"363101330000","dailyChange":0,"weeklyChange":0,"side":"-"},{"timestamp":"1702429200","name":"Chocolate-Flint-Falcon","profit":"148363230756","dailyChange":0,"weeklyChange":0,"side":"-"},{"timestamp":"1702429200","name":"Crypto Research","profit":"176454784734","dailyChange":0,"weeklyChange":0,"side":"-"},{"timestamp":"1702429200","name":"Disco-Solar-Fang","profit":"273785273017","dailyChange":-2885092,"weeklyChange":567891480,"side":"Long"},{"timestamp":"1702429200","name":"Fern-Ebony-Slave","profit":"132547494767","dailyChange":0,"weeklyChange":0,"side":"-"},{"timestamp":"1702429200","name":"Honeysuckle-South-Rib","profit":"197802789481","dailyChange":0,"weeklyChange":0,"side":"-"},{"timestamp":"1702429200","name":"Hot-Relic-Fancier","profit":"421651590744","dailyChange":0,"weeklyChange":0,"side":"-"},{"timestamp":"1702429200","name":"Linen","profit":"126169224872","dailyChange":-318,"weeklyChange":9847,"side":"Long"},{"timestamp":"1702429200","name":"Mercury-Wood-Sprite","profit":"848333808919","dailyChange":0,"weeklyChange":0,"side":"-"},{"timestamp":"1702429200","name":"Paper-Feather-Stallion","profit":"405461699789","dailyChange":0,"weeklyChange":0,"side":"-"},{"timestamp":"1702429200","name":"Prairie-Ballistic-Palm","profit":"98784299271","dailyChange":6686,"weeklyChange":-170270535,"side":"Short"},{"timestamp":"1702429200","name":"Prong-Buttercup-Whale","profit":"110542245449","dailyChange":0,"weeklyChange":0,"side":"-"},{"timestamp":"1702429200","name":"Quill-Rift-Hoof","profit":"176869595406","dailyChange":9446223,"weeklyChange":-33846554,"side":"Short"},{"timestamp":"1702429200","name":"Ripple-Great-Koala","profit":"138066538479","dailyChange":143758394,"weeklyChange":34423876,"side":"Short"},{"timestamp":"1702429200","name":"Shubhodeep Das","profit":"197561007709","dailyChange":0,"weeklyChange":0,"side":"-"},{"timestamp":"1702429200","name":"Skitter-Peridot-Raven","profit":"165801269805","dailyChange":0,"weeklyChange":0,"side":"-"},{"timestamp":"1702429200","name":"SuDoResearch","profit":"127477304991","dailyChange":0,"weeklyChange":0,"side":"-"},{"timestamp":"1702429200","name":"Winter-Pink-Fang","profit":"123861815224","dailyChange":0,"weeklyChange":0,"side":"-"},{"timestamp":"1702429200","name":"aoa","profit":"362146477713","dailyChange":-17640831,"weeklyChange":-4511356496,"side":"Long"},{"timestamp":"1702429200","name":"fhrp","profit":"331620529937","dailyChange":0,"weeklyChange":0,"side":"-"},{"timestamp":"1702429200","name":"xorq","profit":"127811730513","dailyChange":0,"weeklyChange":0,"side":"-"}]}