{"success":true,"data":[{"timestamp":"1697850000","name":"3dudescapital","profit":"251901700043","dailyChange":-3378043,"weeklyChange":28032436,"side":"Short"},{"timestamp":"1697850000","name":"Amber Group","profit":"100702451871","dailyChange":0,"weeklyChange":0,"side":"-"},{"timestamp":"1697850000","name":"Bog-Pear-Weasel","profit":"322983499410","dailyChange":109733284,"weeklyChange":72354730,"side":"Long"},{"timestamp":"1697850000","name":"Bramble-Dark-Grasp","profit":"188700698523","dailyChange":0,"weeklyChange":0,"side":"-"},{"timestamp":"1697850000","name":"Chatter-Paper-Snout","profit":"363101330000","dailyChange":0,"weeklyChange":0,"side":"-"},{"timestamp":"1697850000","name":"Chocolate-Flint-Falcon","profit":"148363230756","dailyChange":0,"weeklyChange":0,"side":"-"},{"timestamp":"1697850000","name":"Crypto Research","profit":"176454784734","dailyChange":0,"weeklyChange":0,"side":"-"},{"timestamp":"1697850000","name":"Disco-Solar-Fang","profit":"266212196006","dailyChange":1105182,"weeklyChange":-9171267,"side":"Long"},{"timestamp":"1697850000","name":"Fern-Ebony-Slave","profit":"132547494767","dailyChange":0,"weeklyChange":0,"side":"-"},{"timestamp":"1697850000","name":"Honeysuckle-South-Rib","profit":"197802789481","dailyChange":0,"weeklyChange":0,"side":"-"},{"timestamp":"1697850000","name":"Hot-Relic-Fancier","profit":"421651590744","dailyChange":0,"weeklyChange":0,"side":"-"},{"timestamp":"1697850000","name":"Linen","profit":"125134353457","dailyChange":170846867,"weeklyChange":177746562,"side":"Long"},{"timestamp":"1697850000","name":"Mercury-Wood-Sprite","profit":"848333808919","dailyChange":0,"weeklyChange":-160556,"side":"-"},{"timestamp":"1697850000","name":"Paper-Feather-Stallion","profit":"405461699789","dailyChange":0,"weeklyChange":0,"side":"-"},{"timestamp":"1697850000","name":"Prairie-Ballistic-Palm","profit":"98928433417","dailyChange":0,"weeklyChange":0,"side":"-"},{"timestamp":"1697850000","name":"Prong-Buttercup-Whale","profit":"110542245449","dailyChange":0,"weeklyChange":0,"side":"-"},{"timestamp":"1697850000","name":"Quill-Rift-Hoof","profit":"176900995430","dailyChange":0,"weeklyChange":0,"side":"-"},{"timestamp":"1697850000","name":"Ripple-Great-Koala","profit":"138001266650","dailyChange":7278263,"weeklyChange":-2693358,"side":"Long"},{"timestamp":"1697850000","name":"Shubhodeep Das","profit":"197561007709","dailyChange":0,"weeklyChange":0,"side":"-"},{"timestamp":"1697850000","name":"Skitter-Peridot-Raven","profit":"165801269805","dailyChange":0,"weeklyChange":0,"side":"-"},{"timestamp":"1697850000","name":"SuDoResearch","profit":"127477304991","dailyChange":0,"weeklyChange":0,"side":"-"},{"timestamp":"1697850000","name":"Winter-Pink-Fang","profit":"123861815224","dailyChange":0,"weeklyChange":0,"side":"-"},{"timestamp":"1697850000","name":"aoa","profit":"406674860005","dailyChange":12613826,"weeklyChange":184485654,"side":"Long"},{"timestamp":"1697850000","name":"fhrp","profit":"331620529937","dailyChange":0,"weeklyChange":0,"side":"-"},{"timestamp":"1697850000","name":"xorq","profit":"127811730513","dailyChange":0,"weeklyChange":0,"side":"-"}]}